mailstream/__init__.py
mailstream/client.py
mailstream/context.py
mailstream/exceptions.py
mailstream/mail.py
mailstream-0.1.6.dist-info/LICENSE
mailstream-0.1.6.dist-info/METADATA
mailstream-0.1.6.dist-info/WHEEL
mailstream-0.1.6.dist-info/top_level.txt
mailstream-0.1.6.dist-info/RECORD
