Metadata-Version: 2.1
Name: mailstream
Version: 0.1.6
Summary: Async IMAP client for streaming email messages
Home-page: https://github.com/christianobora/mailstream
Author: Christian Obora
Author-email: christianobora@uchicago.edu
Requires-Python: >=3.8
License-File: LICENSE
Requires-Dist: aioimaplib>=1.0.0
Provides-Extra: dev
Requires-Dist: pytest>=8.3.4; extra == "dev"
Requires-Dist: pytest-asyncio>=0.16.0; extra == "dev"
Requires-Dist: mypy>=1.0.0; extra == "dev"
Requires-Dist: black>=24.10.0; extra == "dev"
Requires-Dist: flake8>=7.1.1; extra == "dev"
Provides-Extra: examples
Requires-Dist: openai>=1.0.0; extra == "examples"
Requires-Dist: beautifulsoup4>=4.10.0; extra == "examples"
